LICENSE
MANIFEST.in
README.rst
setup.py
/Users/dpbroberg/Documents/research/research_codes/pycdcd/scripts/pycdt
pycdt/__init__.py
pycdt.egg-info/PKG-INFO
pycdt.egg-info/SOURCES.txt
pycdt.egg-info/dependency_links.txt
pycdt.egg-info/requires.txt
pycdt.egg-info/top_level.txt
pycdt/core/__init__.py
pycdt/core/chemical_potentials.py
pycdt/core/defects_analyzer.py
pycdt/core/defectsmaker.py
pycdt/corrections/__init__.py
pycdt/corrections/finite_size_charge_correction.py
pycdt/corrections/freysoldt_correction.py
pycdt/corrections/freysoldt_plotter.py
pycdt/corrections/kumagai_correction.py
pycdt/corrections/ldau_correction.py
pycdt/corrections/sxdefect_correction.py
pycdt/corrections/utils.py
pycdt/utils/DefectSet.yaml
pycdt/utils/__init__.py
pycdt/utils/example_single_file_path_parse.py
pycdt/utils/log_util.py
pycdt/utils/logging.yaml
pycdt/utils/parse_calculations.py
pycdt/utils/plotter.py
pycdt/utils/units.py
pycdt/utils/vasp.py