Metadata-Version: 1.2
Name: pycdt
Version: 2.0.2
Summary: PyCDT is a python package to facilitate DFT calculations for point defects in solids
Home-page: UNKNOWN
Author: Danny Broberg, Bharat Medasani, Nils Zimmerman
Author-email: mbkumar@gmail.com
Maintainer: Bharat Medasani
Maintainer-email: mbkumar@gmail.com
License: MIT
Platform: UNKNOWN
Classifier: Programming Language :: Python :: 2
Classifier: Programming Language :: Python :: 2.7
Classifier: Programming Language :: Python :: 3
Classifier: Programming Language :: Python :: 3.6
Classifier: Intended Audience :: Science/Research
Classifier: License :: OSI Approved :: MIT License
Classifier: Operating System :: OS Independent
Classifier: Topic :: Scientific/Engineering :: Information Analysis
Classifier: Topic :: Scientific/Engineering :: Physics
Classifier: Topic :: Scientific/Engineering :: Chemistry
Classifier: Topic :: Software Development :: Libraries :: Python Modules
